rsptx/build_tools/__init__.py
rsptx/build_tools/core.py
rsptx/cl_utils/__init__.py
rsptx/cl_utils/core.py
rsptx/configuration/.DS_Store
rsptx/configuration/__init__.py
rsptx/configuration/core.py
rsptx/db/.ruff_cache/.gitignore
rsptx/db/.ruff_cache/CACHEDIR.TAG
rsptx/db/.ruff_cache/content/895fda5609e2f73d
rsptx/db/.ruff_cache/content/97776eeb3613080b
rsptx/db/__init__.py
rsptx/db/async_session.py
rsptx/db/core.py
rsptx/db/crud.py
rsptx/db/models.py
rsptx/logging/__init__.py
rsptx/logging/applogger.py
rsptx/logging/core.py
rsptx/response_helpers/__init__.py
rsptx/response_helpers/core.py
rsptx/rsmanage/.ruff_cache/.gitignore
rsptx/rsmanage/.ruff_cache/.update-informer
rsptx/rsmanage/.ruff_cache/CACHEDIR.TAG
rsptx/rsmanage/.ruff_cache/content/2a4b723e63e7a02b
rsptx/rsmanage/.ruff_cache/content/92f53d3a4ad427c5
rsptx/rsmanage/__init__.py
rsptx/rsmanage/core.py
rsptx/validation/__init__.py
rsptx/validation/core.py
rsptx/validation/schemas.py
rsmanage-2.0.0.dist-info/METADATA
rsmanage-2.0.0.dist-info/WHEEL
rsmanage-2.0.0.dist-info/entry_points.txt
rsmanage-2.0.0.dist-info/RECORD
