Metadata-Version: 2.1
Name: rsmanage
Version: 2.0.0
Summary: 
Author: Brad Miller
Author-email: bonelake@mac.com
Requires-Python: >=3.10,<4.0
Classifier: Programming Language :: Python :: 3
Classifier: Programming Language :: Python :: 3.10
Classifier: Programming Language :: Python :: 3.11
Requires-Dist: anyio (>=3.6.2,<4.0.0)
Requires-Dist: asyncclick (>=8.1.3.4,<9.0.0.0)
Requires-Dist: asyncpg (>=0.27.0,<0.28.0)
Requires-Dist: fastapi (>=0.95.0,<0.96.0)
Requires-Dist: greenlet (>=2.0.2,<3.0.0)
Requires-Dist: lxml (>=4.9.2,<5.0.0)
Requires-Dist: myst-parser (>=1.0.0,<2.0.0)
Requires-Dist: paver (>=1.3.4,<2.0.0)
Requires-Dist: pgcli (>=3.5.0,<4.0.0)
Requires-Dist: psycopg2-binary (>=2.9.6,<3.0.0)
Requires-Dist: pydal (>=20221110.1,<20221111.0)
Requires-Dist: pydantic[dotenv] (>=1.10.7,<2.0.0)
Requires-Dist: pyhumps (>=3.8.0,<4.0.0)
Requires-Dist: python-dotenv (>=1.0.0,<2.0.0)
Requires-Dist: redis (>=4.5.4,<5.0.0)
Requires-Dist: runestone (>=7.0.0,<8.0.0)
Requires-Dist: sphinx-reredirects (>=0.1.2,<0.2.0)
Requires-Dist: sphinxcontrib-paverutils (>=1.17.0,<2.0.0)
Requires-Dist: sqlalchemy (>=1.4.0,<2.0.0)
